concrete_settings/__init__.py
concrete_settings/behaviors/__init__.py
concrete_settings/behaviors/behavior.py
concrete_settings/behaviors/override.py
concrete_settings/behaviors/validate.py
concrete_settings/contrib/__init__.py
concrete_settings/contrib/behaviors/__init__.py
concrete_settings/contrib/behaviors/deprecated_behavior.py
concrete_settings/contrib/behaviors/required_behavior.py
concrete_settings/contrib/frameworks/__init__.py
concrete_settings/contrib/frameworks/django30.py
concrete_settings/contrib/frameworks/django30_template.py
concrete_settings/contrib/frameworks/django30_template.yml
concrete_settings/contrib/sources/__init__.py
concrete_settings/contrib/sources/envvar_source.py
concrete_settings/contrib/sources/json_source.py
concrete_settings/contrib/sources/python_source.py
concrete_settings/contrib/sources/yaml_source.py
concrete_settings/contrib/validators/__init__.py
concrete_settings/contrib/validators/deprecated_validator.py
concrete_settings/docreader.py
concrete_settings/exceptions.py
concrete_settings/settings.py
concrete_settings/sources/__init__.py
concrete_settings/sources/strategies.py
concrete_settings/types.py
concrete_settings/validators/__init__.py
concrete_settings/validators/required_validator.py
concrete_settings/validators/validator.py
concrete_settings/validators/value_type_validator.py
concrete_settings-0.1.dist-info/LICENSE
concrete_settings-0.1.dist-info/WHEEL
concrete_settings-0.1.dist-info/METADATA
concrete_settings-0.1.dist-info/RECORD
