Metadata-Version: 2.1
Name: concrete-settings
Version: 0.1
Summary: Concrete Settings facilitates configuration management in big and small projects.
Home-page: https://github.com/basicwolf/concrete-settings
License: MIT
Keywords: settings,configuration
Author: Zaur Nasibov
Author-email: comments@znasibov.info
Requires-Python: >=3.6,<4.0
Classifier: License :: OSI Approved :: MIT License
Classifier: Programming Language :: Python :: 3
Classifier: Programming Language :: Python :: 3.6
Classifier: Programming Language :: Python :: 3.7
Classifier: Programming Language :: Python :: 3.8
Provides-Extra: pyyaml
Requires-Dist: pyyaml (>=5.3,<6.0); extra == "pyyaml"
Requires-Dist: sphinx (>=3.0,<4.0)
Requires-Dist: typeguard (>=2.7,<3.0)
Requires-Dist: typing_extensions (>=3.7.4,<4.0.0)
Project-URL: Repository, https://github.com/basicwolf/concrete-settings
